apps/__init__.py
apps/monero/__init__.py
apps/monero/controller/__init__.py
apps/monero/protocol/__init__.py
apps/monero/xmr/__init__.py
apps/monero/xmr/sub/__init__.py
monero_glue/__init__.py
monero_glue/protobuf.py
monero_glue/agent/__init__.py
monero_glue/agent/agent_lite.py
monero_glue/agent/agent_misc.py
monero_glue/compat/__init__.py
monero_glue/compat/collections.py
monero_glue/compat/gc.py
monero_glue/compat/log.py
monero_glue/compat/micropython.py
monero_glue/compat/utils.py
monero_glue/hwtoken/__init__.py
monero_glue/hwtoken/iface.py
monero_glue/hwtoken/misc.py
monero_glue/hwtoken/token.py
monero_glue/messages/Address.py
monero_glue/messages/ApplyFlags.py
monero_glue/messages/ApplySettings.py
monero_glue/messages/BackupDevice.py
monero_glue/messages/BackupType.py
monero_glue/messages/BinanceAddress.py
monero_glue/messages/BinanceCancelMsg.py
monero_glue/messages/BinanceCoin.py
monero_glue/messages/BinanceGetAddress.py
monero_glue/messages/BinanceGetPublicKey.py
monero_glue/messages/BinanceInputOutput.py
monero_glue/messages/BinanceOrderMsg.py
monero_glue/messages/BinanceOrderSide.py
monero_glue/messages/BinanceOrderType.py
monero_glue/messages/BinancePublicKey.py
monero_glue/messages/BinanceSignTx.py
monero_glue/messages/BinanceSignedTx.py
monero_glue/messages/BinanceTimeInForce.py
monero_glue/messages/BinanceTransferMsg.py
monero_glue/messages/BinanceTxRequest.py
monero_glue/messages/ButtonAck.py
monero_glue/messages/ButtonRequest.py
monero_glue/messages/ButtonRequestType.py
monero_glue/messages/Cancel.py
monero_glue/messages/Capability.py
monero_glue/messages/CardanoAddress.py
monero_glue/messages/CardanoGetAddress.py
monero_glue/messages/CardanoGetPublicKey.py
monero_glue/messages/CardanoPublicKey.py
monero_glue/messages/CardanoSignTx.py
monero_glue/messages/CardanoSignedTx.py
monero_glue/messages/CardanoTxAck.py
monero_glue/messages/CardanoTxInputType.py
monero_glue/messages/CardanoTxOutputType.py
monero_glue/messages/CardanoTxRequest.py
monero_agent-3.0.1.dist-info/LICENSE
monero_agent-3.0.1.dist-info/LICENSE-OLD
monero_agent-3.0.1.dist-info/METADATA
monero_agent-3.0.1.dist-info/WHEEL
monero_agent-3.0.1.dist-info/entry_points.txt
monero_agent-3.0.1.dist-info/top_level.txt
monero_agent-3.0.1.dist-info/RECORD
