Metadata-Version: 2.1
Name: monero-agent
Version: 3.0.1
Summary: Monero Agent
Home-page: https://github.com/ph4r05/monero-agent
Author: Dusan Klinec
Author-email: dusan.klinec@gmail.com
License: MIT
Platform: UNKNOWN
Classifier: Development Status :: 3 - Alpha
Classifier: Intended Audience :: Developers
Classifier: Programming Language :: Python
Classifier: Programming Language :: Python :: 3.5
Classifier: Programming Language :: Python :: 3.6
Classifier: Topic :: Security
Requires-Python: >=3.5
Requires-Dist: monero-serialize (>=3.0.1)
Requires-Dist: pycryptodome
Requires-Dist: py-cryptonight (>=0.1.2)
Requires-Dist: chacha20poly1305
Provides-Extra: dev
Requires-Dist: nose ; extra == 'dev'
Requires-Dist: pep8 ; extra == 'dev'
Requires-Dist: tox ; extra == 'dev'
Requires-Dist: aiounittest ; extra == 'dev'
Requires-Dist: requests ; extra == 'dev'
Requires-Dist: pympler ; extra == 'dev'
Requires-Dist: pypandoc ; extra == 'dev'
Requires-Dist: pandoc ; extra == 'dev'
Requires-Dist: pip ; extra == 'dev'
Requires-Dist: pycparser ; extra == 'dev'
Requires-Dist: ctypeslib2 ; extra == 'dev'
Requires-Dist: cryptography ; extra == 'dev'
Requires-Dist: protobuf (==3.4.0) ; extra == 'dev'
Provides-Extra: docs
Requires-Dist: Sphinx (>=1.0) ; extra == 'docs'
Requires-Dist: sphinx-rtd-theme ; extra == 'docs'
Requires-Dist: sphinxcontrib-programoutput ; extra == 'docs'
Provides-Extra: poc
Requires-Dist: ecdsa ; extra == 'poc'
Requires-Dist: asyncio ; extra == 'poc'
Requires-Dist: requests ; extra == 'poc'
Requires-Dist: cmd2 (>=0.6.9) ; extra == 'poc'
Requires-Dist: shellescape ; extra == 'poc'
Requires-Dist: coloredlogs ; extra == 'poc'
Requires-Dist: blessed (>=1.14.1) ; extra == 'poc'
Requires-Dist: flask (>=0.12) ; extra == 'poc'
Requires-Dist: flask-socketio ; extra == 'poc'
Requires-Dist: eventlet ; extra == 'poc'
Requires-Dist: gevent ; extra == 'poc'
Requires-Dist: sarge (>=0.1.5) ; extra == 'poc'
Provides-Extra: tcry
Requires-Dist: py-trezor-crypto-ph4 (==0.1.1) ; extra == 'tcry'
Provides-Extra: trezor
Requires-Dist: trezor ; extra == 'trezor'
